bta_lib-0.9.8.dist-info/DESCRIPTION.rst
bta_lib-0.9.8.dist-info/METADATA
bta_lib-0.9.8.dist-info/RECORD
bta_lib-0.9.8.dist-info/WHEEL
bta_lib-0.9.8.dist-info/metadata.json
bta_lib-0.9.8.dist-info/top_level.txt
btalib/__init__.py
btalib/config.py
btalib/errors.py
btalib/indicator.py
btalib/pandas.py
btalib/utils.py
btalib/version.py
btalib/indicators/__init__.py
btalib/indicators/ad.py
btalib/indicators/aroon.py
btalib/indicators/atr.py
btalib/indicators/bbands.py
btalib/indicators/beta.py
btalib/indicators/bop.py
btalib/indicators/cci.py
btalib/indicators/cmo.py
btalib/indicators/correl.py
btalib/indicators/crossover.py
btalib/indicators/dema.py
btalib/indicators/directionalmove.py
btalib/indicators/ema.py
btalib/indicators/ewma.py
btalib/indicators/ht_dcperiod.py
btalib/indicators/ht_dcphase.py
btalib/indicators/ht_phasor.py
btalib/indicators/ht_sine.py
btalib/indicators/ht_trendline.py
btalib/indicators/ht_trendmode.py
btalib/indicators/kama.py
btalib/indicators/linreg.py
btalib/indicators/macd.py
btalib/indicators/madev.py
btalib/indicators/mama.py
btalib/indicators/math.py
btalib/indicators/mathop.py
btalib/indicators/mavp.py
btalib/indicators/mfi.py
btalib/indicators/midpoint.py
btalib/indicators/mom.py
btalib/indicators/obv.py
btalib/indicators/ppo.py
btalib/indicators/price.py
btalib/indicators/roc.py
btalib/indicators/rsi.py
btalib/indicators/sma.py
btalib/indicators/smma.py
btalib/indicators/stddev.py
btalib/indicators/stochastic.py
btalib/indicators/stochrsi.py
btalib/indicators/t3.py
btalib/indicators/tema.py
btalib/indicators/trima.py
btalib/indicators/trix.py
btalib/indicators/ultimateoscillator.py
btalib/indicators/var.py
btalib/indicators/williamsr.py
btalib/indicators/wma.py
btalib/meta/__init__.py
btalib/meta/aliases.py
btalib/meta/docs.py
btalib/meta/groups.py
btalib/meta/inputs.py
btalib/meta/lines.py
btalib/meta/linesholder.py
btalib/meta/linesops.py
btalib/meta/metadata.py
btalib/meta/outputs.py
btalib/meta/params.py
