Metadata-Version: 2.0
Name: bta-lib
Version: 0.9.8
Summary: bta-lib technical analysis library
Home-page: https://github.com/mementum/bta-lib
Author: Daniel Rodriguez
License: MIT
Download-URL: https://github.com/mementum/bta-lib/tarball/0.9.8
Keywords: trading,development,backtesting,algotrading,technical analysis
Platform: UNKNOWN
Classifier: Development Status :: 5 - Production/Stable
Classifier: Intended Audience :: Developers
Classifier: Intended Audience :: Financial and Insurance Industry
Classifier: Topic :: Software Development
Classifier: Topic :: Office/Business :: Financial
Classifier: License :: OSI Approved :: MIT License
Classifier: Programming Language :: Python :: 3.6
Classifier: Programming Language :: Python :: 3.7
Classifier: Programming Language :: Python :: 3.8
Classifier: Operating System :: OS Independent
Requires-Python: >=3.6
Requires-Dist: pandas
